up42/__init__.py
up42/asset.py
up42/base.py
up42/catalog.py
up42/data/aoi_berlin.geojson
up42/data/aoi_washington.geojson
up42/glossary.py
up42/host.py
up42/http/__init__.py
up42/http/client.py
up42/http/config.py
up42/http/http_adapter.py
up42/http/oauth.py
up42/http/session.py
up42/initialization.py
up42/order.py
up42/order_template.py
up42/processing.py
up42/processing_templates.py
up42/stac.py
up42/storage.py
up42/tasking.py
up42/tools.py
up42/utils.py
up42/version/version_control.py
up42/webhooks.py
up42_py-2.6.0.dist-info/LICENSE
up42_py-2.6.0.dist-info/METADATA
up42_py-2.6.0.dist-info/WHEEL
up42_py-2.6.0.dist-info/RECORD
