Metadata-Version: 2.3
Name: up42-py
Version: 2.6.0
Summary: Python SDK for UP42, the geospatial marketplace and developer platform.
License: https://github.com/up42/up42-py/blob/master/LICENSE
Author: UP42 GmbH
Author-email: support@up42.com
Requires-Python: >=3.9,<4
Classifier: Development Status :: 4 - Beta
Classifier: Intended Audience :: Developers
Classifier: License :: OSI Approved :: MIT License
Classifier: License :: Other/Proprietary License
Classifier: Operating System :: OS Independent
Classifier: Programming Language :: Python :: 3
Classifier: Programming Language :: Python :: 3.9
Classifier: Programming Language :: Python :: 3.10
Classifier: Programming Language :: Python :: 3.11
Classifier: Programming Language :: Python :: 3.12
Classifier: Programming Language :: Python :: 3.13
Requires-Dist: geojson (==3.1.0)
Requires-Dist: geopandas (<2)
Requires-Dist: pystac-client (>=0.7.2,<0.8.0)
Requires-Dist: requests (>=2.32.4,<3.0.0)
Requires-Dist: tenacity (==8.4.1)
Requires-Dist: tqdm (>=4.66.0,<5.0.0)
Requires-Dist: urllib3 (>=2.5.0,<3.0.0)
